{
    "resetFormOnClick": true,
    "boxShadow": "none",
    "mobileBottomRow": 37,
    "widgetName": "Button2",
    "onClick": "{{UpdateUser.run();navigateTo('Step1StateMap')}}",
    "buttonColor": "{{appsmith.theme.colors.primaryColor}}",
    "dynamicPropertyPathList": [
        {"key": "isDisabled"},
        {"key": "onClick"}
    ],
    "displayName": "Button",
    "iconSVG": "https://appcdn.appsmith.com/static/media/icon.05d209fafeb13a8569e3b4e97069d9ee.svg",
    "searchTags": [
        "click",
        "submit"
    ],
    "topRow": 59,
    "bottomRow": 64,
    "type": "BUTTON_WIDGET",
    "hideCard": false,
    "mobileRightColumn": 62,
    "animateLoading": true,
    "dynamicTriggerPathList": [{"key": "onClick"}],
    "leftColumn": 19,
    "dynamicBindingPathList": [
        {"key": "buttonColor"},
        {"key": "borderRadius"},
        {"key": "isDisabled"}
    ],
    "text": "Create Account",
    "isDisabled": "{{!appsmith.store.type}}",
    "key": "oexc5j4b2o",
    "isDeprecated": false,
    "rightColumn": 48,
    "isDefaultClickDisabled": true,
    "widgetId": "mx3za8lclt",
    "minWidth": 120,
    "isVisible": true,
    "recaptchaType": "V3",
    "version": 1,
    "parentId": "lb2hx8ghdc",
    "tags": ["Buttons"],
    "renderMode": "CANVAS",
    "isLoading": false,
    "mobileTopRow": 33,
    "responsiveBehavior": "hug",
    "originalTopRow": 57,
    "disabledWhenInvalid": true,
    "borderRadius": "{{appsmith.theme.borderRadius.appBorderRadius}}",
    "mobileLeftColumn": 46,
    "originalBottomRow": 62,
    "buttonVariant": "PRIMARY",
    "placement": "CENTER"
}