{
    "mobileBottomRow": 55,
    "widgetName": "Text1",
    "borderColor": "#f4f4f5",
    "displayName": "Text",
    "iconSVG": "https://appcdn.appsmith.com/static/media/icon.c3b6033f570046f8c6288d911333a827.svg",
    "searchTags": [
        "typography",
        "paragraph",
        "label"
    ],
    "topRow": 85,
    "bottomRow": 89,
    "parentRowSpace": 10,
    "type": "TEXT_WIDGET",
    "hideCard": false,
    "mobileRightColumn": 26,
    "animateLoading": true,
    "overflow": "NONE",
    "fontFamily": "{{appsmith.theme.fontFamily.appFont}}",
    "parentColumnSpace": 10,
    "dynamicTriggerPathList": [],
    "leftColumn": 8,
    "dynamicBindingPathList": [
        {"key": "truncateButtonColor"},
        {"key": "fontFamily"},
        {"key": "borderRadius"},
        {"key": "text"}
    ],
    "shouldTruncate": false,
    "borderWidth": "2",
    "truncateButtonColor": "{{appsmith.theme.colors.primaryColor}}",
    "text": "{{String((appsmith.store.zipShow))}}",
    "key": "1yl1nwu336",
    "isDeprecated": false,
    "rightColumn": 62,
    "textAlign": "LEFT",
    "dynamicHeight": "AUTO_HEIGHT",
    "widgetId": "p5lglz77xj",
    "minWidth": 450,
    "isVisible": true,
    "fontStyle": "BOLD",
    "textColor": "#231F20",
    "version": 1,
    "parentId": "08qntok3nx",
    "renderMode": "CANVAS",
    "isLoading": false,
    "mobileTopRow": 51,
    "responsiveBehavior": "fill",
    "originalTopRow": 85,
    "borderRadius": "{{appsmith.theme.borderRadius.appBorderRadius}}",
    "mobileLeftColumn": 10,
    "maxDynamicHeight": 9000,
    "originalBottomRow": 89,
    "fontSize": "1.25rem",
    "minDynamicHeight": 4
}